poc_dependency_gob/.DS_Store
poc_dependency_gob/__init__.py
poc_dependency_gob/one/__init__.py
poc_dependency_gob/one/test_function.py
poc_dependency_gob/three/__init__.py
poc_dependency_gob/three/fn_three.py
poc_dependency_gob/two/__init__.py
poc_dependency_gob-0.2.0.dist-info/WHEEL
poc_dependency_gob-0.2.0.dist-info/METADATA
poc_dependency_gob-0.2.0.dist-info/RECORD
